cgtn_videos/__init__.py
cgtn_videos/channel.py
cgtn_videos/config.py
cgtn_videos/video.py
cgtn_videos/english/__init__.py
cgtn_videos/english/news.py
cgtn_videos/english/newscategory.py
cgtn_videos/english/newsspecial.py
cgtn_videos/english/program.py
cgtn_videos/other/__init__.py
cgtn_videos/other/section.py
cgtn_videos-0.0.4.dist-info/LICENSE
cgtn_videos-0.0.4.dist-info/METADATA
cgtn_videos-0.0.4.dist-info/WHEEL
cgtn_videos-0.0.4.dist-info/top_level.txt
cgtn_videos-0.0.4.dist-info/RECORD
