Metadata-Version: 2.1
Name: cgtn-videos
Version: 0.0.4
Summary: Python package fetch the video URLs and metadata from CGTN website
Home-page: https://github.com/boeboe/cgtn-videos
Author: Bart Van Bos
Author-email: bartvanbos@gmail.com
License: MIT
Keywords: china chinese cgtn video kodi xbmc
Platform: UNKNOWN
Classifier: Development Status :: 5 - Production/Stable
Classifier: Intended Audience :: Developers
Classifier: Natural Language :: English
Classifier: License :: OSI Approved :: MIT License
Classifier: Programming Language :: Python
Classifier: Programming Language :: Python :: 2
Classifier: Programming Language :: Python :: 3
Classifier: Topic :: Software Development :: Libraries :: Python Modules
Classifier: Topic :: System :: Software Distribution
